z048/app.py
z048/utils.py
z048-0.1.2.dist-info/entry_points.txt
z048-0.1.2.dist-info/WHEEL
z048-0.1.2.dist-info/METADATA
z048-0.1.2.dist-info/RECORD
