Metadata-Version: 2.1
Name: z048
Version: 0.1.2
Summary: The game 2048 - CLI version!!
Home-page: https://github.com/sivanbecker/2048
Author: Sivan Becker
Author-email: sivanbecker@gmail.com
Requires-Python: >=3.6,<4.0
Classifier: Programming Language :: Python :: 3
Classifier: Programming Language :: Python :: 3.6
Classifier: Programming Language :: Python :: 3.7
Classifier: Programming Language :: Python :: 3.8
Requires-Dist: click (>=7.1.2,<8.0.0)
Requires-Dist: numpy (>=1.18.5,<2.0.0)
Project-URL: Repository, https://github.com/sivanbecker/2048
